caesartool/__init__.py
caesartool/__main__.py
caesartool/cipher.py
caesartool/cli.py
caesartool-0.1.6.dist-info/licenses/LICENSE.txt
caesartool-0.1.6.dist-info/METADATA
caesartool-0.1.6.dist-info/WHEEL
caesartool-0.1.6.dist-info/entry_points.txt
caesartool-0.1.6.dist-info/top_level.txt
caesartool-0.1.6.dist-info/RECORD
