Metadata-Version: 2.4
Name: caesartool
Version: 0.1.6
Summary: A Caesar Cipher encryption and decryption program
Home-page: https://github.com/ftkovr9k/Caesar-Encryption-Program
Author: Farhan Khan
Author-email: ftkover9k@gmail.com
Classifier: Programming Language :: Python :: 3.13
Classifier: License :: OSI Approved :: MIT License
Classifier: Operating System :: OS Independent
License-File: LICENSE.txt
Dynamic: author
Dynamic: author-email
Dynamic: classifier
Dynamic: description
Dynamic: description-content-type
Dynamic: home-page
Dynamic: license-file
Dynamic: summary
